MANIFEST.in
README.md
setup.py
PasswordGeneratorTool/__init__.py
PasswordGeneratorTool/main.py
PasswordGeneratorTool.egg-info/PKG-INFO
PasswordGeneratorTool.egg-info/SOURCES.txt
PasswordGeneratorTool.egg-info/dependency_links.txt
PasswordGeneratorTool.egg-info/top_level.txt