Metadata-Version: 2.1
Name: PasswordGeneratorTool
Version: 0.3.0
Summary: Tool that will generate password from given length
Author: Daniel Czarnecki
Author-email: Daniel.Czarnecki.94@wp.pl
